openpmd_beamphysics-0.13.1.dist-info/licenses/LICENSE
pmd_beamphysics/__init__.py
pmd_beamphysics/_version.py
pmd_beamphysics/labels.py
pmd_beamphysics/particles.py
pmd_beamphysics/plot.py
pmd_beamphysics/readers.py
pmd_beamphysics/species.py
pmd_beamphysics/statistics.py
pmd_beamphysics/status.py
pmd_beamphysics/testing.py
pmd_beamphysics/tools.py
pmd_beamphysics/units.py
pmd_beamphysics/utils.py
pmd_beamphysics/writers.py
pmd_beamphysics/fields/__init__.py
pmd_beamphysics/fields/analysis.py
pmd_beamphysics/fields/conversion.py
pmd_beamphysics/fields/corrector_modeling.py
pmd_beamphysics/fields/expansion.py
pmd_beamphysics/fields/fieldmesh.py
pmd_beamphysics/fields/solenoid.py
pmd_beamphysics/interfaces/__init__.py
pmd_beamphysics/interfaces/ansys.py
pmd_beamphysics/interfaces/astra.py
pmd_beamphysics/interfaces/bmad.py
pmd_beamphysics/interfaces/cst.py
pmd_beamphysics/interfaces/elegant.py
pmd_beamphysics/interfaces/genesis.py
pmd_beamphysics/interfaces/gpt.py
pmd_beamphysics/interfaces/impact.py
pmd_beamphysics/interfaces/litrack.py
pmd_beamphysics/interfaces/lucretia.py
pmd_beamphysics/interfaces/opal.py
pmd_beamphysics/interfaces/simion.py
pmd_beamphysics/interfaces/superfish.py
pmd_beamphysics/standards/__init__.py
pmd_beamphysics/standards/statistics.py
pmd_beamphysics/standards/statistics.yaml
pmd_beamphysics/wakefields/__init__.py
pmd_beamphysics/wakefields/base.py
pmd_beamphysics/wakefields/impedance.py
pmd_beamphysics/wakefields/pseudomode.py
pmd_beamphysics/wakefields/tabular.py
pmd_beamphysics/wakefields/resistive_wall/__init__.py
pmd_beamphysics/wakefields/resistive_wall/base.py
pmd_beamphysics/wakefields/resistive_wall/impedance.py
pmd_beamphysics/wakefields/resistive_wall/pseudomode.py
pmd_beamphysics/wavefront/analysis.py
pmd_beamphysics/wavefront/propagators.py
pmd_beamphysics/wavefront/wavefront.py
openpmd_beamphysics-0.13.1.dist-info/METADATA
openpmd_beamphysics-0.13.1.dist-info/WHEEL
openpmd_beamphysics-0.13.1.dist-info/top_level.txt
openpmd_beamphysics-0.13.1.dist-info/RECORD
