Metadata-Version: 2.4
Name: openpmd-beamphysics
Version: 0.13.1
Summary: Tools for analyzing and viewing particle data in the openPMD standard, extension beamphysics.
Author: Christopher Mayes
License:                                  Apache License
Project-URL: Homepage, https://github.com/ChristopherMayes/openPMD-beamphysics
Classifier: Development Status :: 4 - Beta
Classifier: Natural Language :: English
Classifier: Programming Language :: Python :: 3
Classifier: Topic :: Scientific/Engineering
Requires-Python: >=3.9
License-File: LICENSE
Requires-Dist: numpy
Requires-Dist: scipy>=1.0.0
Requires-Dist: matplotlib
Requires-Dist: h5py
Requires-Dist: python-dateutil
Provides-Extra: dev
Requires-Dist: pytest; extra == "dev"
Requires-Dist: pytest-cov; extra == "dev"
Requires-Dist: pytest-benchmark; extra == "dev"
Requires-Dist: pyyaml; extra == "dev"
Provides-Extra: doc
Requires-Dist: mkdocs; extra == "doc"
Requires-Dist: mkdocs-jupyter; extra == "doc"
Requires-Dist: mkdocs-macros-plugin; extra == "doc"
Requires-Dist: mkdocs-material; extra == "doc"
Requires-Dist: mkdocstrings; extra == "doc"
Requires-Dist: mkdocstrings-python; extra == "doc"
Dynamic: license-file
